aiida_nwchem/__init__.py
aiida_nwchem/calculations/__init__.py
aiida_nwchem/calculations/nwchem.py
aiida_nwchem/parsers/__init__.py
aiida_nwchem/parsers/nwchem.py
aiida_nwchem/workflows/__init__.py
aiida_nwchem/workflows/base.py
aiida_nwchem-3.0.1.dist-info/entry_points.txt
aiida_nwchem-3.0.1.dist-info/LICENSE.txt
aiida_nwchem-3.0.1.dist-info/WHEEL
aiida_nwchem-3.0.1.dist-info/METADATA
aiida_nwchem-3.0.1.dist-info/RECORD
